polyaxon_sdk/__init__.py
polyaxon_sdk/api_client.py
polyaxon_sdk/configuration.py
polyaxon_sdk/exceptions.py
polyaxon_sdk/rest.py
polyaxon_sdk/api/__init__.py
polyaxon_sdk/api/agents_v1_api.py
polyaxon_sdk/api/artifacts_stores_v1_api.py
polyaxon_sdk/api/auth_v1_api.py
polyaxon_sdk/api/connections_v1_api.py
polyaxon_sdk/api/dashboards_v1_api.py
polyaxon_sdk/api/organizations_v1_api.py
polyaxon_sdk/api/policies_v1_api.py
polyaxon_sdk/api/presets_v1_api.py
polyaxon_sdk/api/project_dashboards_v1_api.py
polyaxon_sdk/api/project_searches_v1_api.py
polyaxon_sdk/api/projects_v1_api.py
polyaxon_sdk/api/queues_v1_api.py
polyaxon_sdk/api/runs_v1_api.py
polyaxon_sdk/api/schemas_v1_api.py
polyaxon_sdk/api/searches_v1_api.py
polyaxon_sdk/api/service_accounts_v1_api.py
polyaxon_sdk/api/tags_v1_api.py
polyaxon_sdk/api/teams_v1_api.py
polyaxon_sdk/api/users_v1_api.py
polyaxon_sdk/api/versions_v1_api.py
polyaxon_sdk/models/__init__.py
polyaxon_sdk/models/agent_state_response_agent_state.py
polyaxon_sdk/models/protobuf_any.py
polyaxon_sdk/models/protobuf_null_value.py
polyaxon_sdk/models/runtime_error.py
polyaxon_sdk/models/search_view.py
polyaxon_sdk/models/v1_activity.py
polyaxon_sdk/models/v1_activity_probe.py
polyaxon_sdk/models/v1_activity_probe_exec.py
polyaxon_sdk/models/v1_activity_probe_http.py
polyaxon_sdk/models/v1_agent.py
polyaxon_sdk/models/v1_agent_reconcile_body_request.py
polyaxon_sdk/models/v1_agent_resources_request.py
polyaxon_sdk/models/v1_agent_state_response.py
polyaxon_sdk/models/v1_agent_status_body_request.py
polyaxon_sdk/models/v1_analytics_spec.py
polyaxon_sdk/models/v1_artifact_kind.py
polyaxon_sdk/models/v1_artifact_tree.py
polyaxon_sdk/models/v1_artifacts_mount.py
polyaxon_sdk/models/v1_artifacts_type.py
polyaxon_sdk/models/v1_auth.py
polyaxon_sdk/models/v1_auth_type.py
polyaxon_sdk/models/v1_average_stopping_policy.py
polyaxon_sdk/models/v1_bayes.py
polyaxon_sdk/models/v1_bucket_connection.py
polyaxon_sdk/models/v1_build.py
polyaxon_sdk-2.12.0.dist-info/METADATA
polyaxon_sdk-2.12.0.dist-info/WHEEL
polyaxon_sdk-2.12.0.dist-info/top_level.txt
polyaxon_sdk-2.12.0.dist-info/RECORD
