Metadata-Version: 2.4
Name: polyaxon-sdk
Version: 2.12.0
Summary: Polyaxon SDKs and REST API specification.
Home-page: 
Author: Polyaxon sdk
Author-email: contact@polyaxon.com
Keywords: OpenAPI,OpenAPI-Generator,Polyaxon SDKs and REST API specification.
Requires-Dist: urllib3>=1.25.3
Requires-Dist: python-dateutil
Requires-Dist: pydantic
Requires-Dist: aenum
Dynamic: author
Dynamic: author-email
Dynamic: description
Dynamic: description-content-type
Dynamic: keywords
Dynamic: requires-dist
Dynamic: summary
